pycalculix/__init__.py
pycalculix/base_classes.py
pycalculix/cadimporter.py
pycalculix/components.py
pycalculix/connectors.py
pycalculix/dmginstall.sh
pycalculix/environment.py
pycalculix/feamodel.py
pycalculix/geometry.py
pycalculix/installer.py
pycalculix/loads.py
pycalculix/material.py
pycalculix/mesh.py
pycalculix/partmodule.py
pycalculix/problem.py
pycalculix/results_file.py
pycalculix/selector.py
pycalculix/version.py
pycalculix-1.1.2.dist-info/LICENSE.txt
pycalculix-1.1.2.dist-info/METADATA
pycalculix-1.1.2.dist-info/WHEEL
pycalculix-1.1.2.dist-info/entry_points.txt
pycalculix-1.1.2.dist-info/top_level.txt
pycalculix-1.1.2.dist-info/RECORD
