Metadata-Version: 2.1
Name: pycalculix
Version: 1.1.2
Summary: Python 3 library to build and solve finite element analysis (FEA) models in Calculix.
Home-page: http://justinablack.com/pycalculix/
Author: Justin Black
Author-email: justin.a.black@gmail.com
License: UNKNOWN
Keywords: FEA,Finite Element Analysis,Calculix,Mechanical Engineering,CAD
Platform: UNKNOWN
Classifier: Programming Language :: Python
Classifier: Programming Language :: Python :: 3
Classifier: Development Status :: 7 - Inactive
Classifier: Intended Audience :: End Users/Desktop
Classifier: Intended Audience :: Science/Research
Classifier: Intended Audience :: Education
Classifier: License :: OSI Approved :: Apache Software License
Classifier: Operating System :: Microsoft :: Windows
Classifier: Operating System :: POSIX
Classifier: Topic :: Software Development :: Libraries :: Python Modules
Classifier: Topic :: Scientific/Engineering :: Physics
Classifier: Topic :: Scientific/Engineering
Requires-Python: >=3
Requires-Dist: matplotlib (>=1.3.1)
Requires-Dist: numpy
Requires-Dist: dxfgrabber (>=0.8.0)
Requires-Dist: requests
Requires-Dist: pytest
